<?xml version="1.0" encoding="utf-8"?>
<openerp>
    <data>
        <template id="assets_backend" inherit_id="web.assets_backend">
            <xpath expr="." position="inside">
                <script type="text/javascript" src="/openBI/static/lib/loader.js"></script>
                <script type="text/javascript" src="/openBI/static/src/js/views/graph_view.js"></script>
                <script type="text/javascript" src="/openBI/static/src/js/views/graph_widget.js"></script>
            </xpath>
        </template>
    </data>
</openerp>